
总结：
1. 外部类不包含内部类的字节信息，需要单独查看
2. 内部类增加一个指向外部类的变量，并在内部类构造器进行赋值
3. 将内部类变为static后再次查看，已经不再持有外部类的引用了
4. 匿名内部类，增加一个文件 外部类$1.class，每有一个内部类，数字增加1，外部的局部变量声明为final，在构造器时进行赋值，与外部引用相似

https://www.cnblogs.com/JunFengChan/p/9465036.html
含有内部类的代码
```
public class Test {
    public static void main(String[] args)  {
    }

    interface Customer  {
        boolean isVIP();
    
    }

    interface VIP extends Customer{

    }

    class Merchant<T extends Customer> {
        public double actionPrice(double price, T customer) {
            return 0.1;
        }
    }
    class VIPOnlyMerchant extends Merchant<VIP> {
        @Override
        public double actionPrice(double price, VIP customer) {
            return 0.1;
        }
    }
}
```
1.编译Java文件
javac
结果得到两个文件
1 外部类名.class 
2 外部类名$内部类名.class   这个文件名含有特殊字符，在idea不可见，需要在文件管理器中查看

查看外部类字节码
javap -v  out/production/DataStruct/Test.class
外部类不包含内部类的字节信息，需要单独查看
```
Classfile /home/song/WorkSpace/IdeaWorkSpace/DataStruct/out/production/DataStruct/Test.class
  Last modified 2022年3月29日; size 430 bytes
  MD5 checksum 692bd723a93734d836ea71de9de53010
  Compiled from "Test.java"
public class Test
  minor version: 0
  major version: 52
  flags: (0x0021) ACC_PUBLIC, ACC_SUPER
  this_class: #2                          // Test
  super_class: #3                         // java/lang/Object
  interfaces: 0, fields: 0, methods: 2, attributes: 2
Constant pool:
  ....//省略常量池
{
  public Test();
    descriptor: ()V
    flags: (0x0001) ACC_PUBLIC
    Code:
      stack=1, locals=1, args_size=1
         0: aload_0
         1: invokespecial #1                  // Method java/lang/Object."<init>":()V
         4: return
      LineNumberTable:
        line 4: 0
      LocalVariableTable:
        Start  Length  Slot  Name   Signature
            0       5     0  this   LTest;

  public static void main(java.lang.String[]);
    descriptor: ([Ljava/lang/String;)V
    flags: (0x0009) ACC_PUBLIC, ACC_STATIC
    Code:
      stack=0, locals=1, args_size=1
         0: return
      LineNumberTable:
        line 20: 0
      LocalVariableTable:
        Start  Length  Slot  Name   Signature
            0       1     0  args   [Ljava/lang/String;
}
SourceFile: "Test.java"
InnerClasses:
  #5= #4 of #2;                           // VIPOnlyMerchant=class Test$VIPOnlyMerchant of class Test
```

查看内部类字节码  简略信息
javap -v  out/production/DataStruct/Test\$VIPOnlyMerchant.class    //注意：$前面的\转义符号
内部类增加一个final Test this$0;  指向外部类的声明
并且在构造器中进行赋值  2: putfield      #1                  // Field this$0:LTest;
```
Classfile /home/song/WorkSpace/IdeaWorkSpace/DataStruct/out/production/DataStruct/Test$VIPOnlyMerchant.class
  Last modified 2022年3月29日; size 671 bytes
  MD5 checksum eb7eba9005d89511bdfb4897206519c7
  Compiled from "Test.java"
class Test$VIPOnlyMerchant extends Merchant<VIP>
  minor version: 0
  major version: 52
  flags: (0x0020) ACC_SUPER
  this_class: #7                          // Test$VIPOnlyMerchant
  super_class: #8                         // Merchant
  interfaces: 0, fields: 1, methods: 3, attributes: 3
Constant pool:
  ....//省略常量池内容
{
  final Test this$0;
    descriptor: LTest;
    flags: (0x1010) ACC_FINAL, ACC_SYNTHETIC

  Test$VIPOnlyMerchant(Test);
    descriptor: (LTest;)V
    flags: (0x0000)
    Code:
      stack=2, locals=2, args_size=2
         0: aload_0
         1: aload_1
         2: putfield      #1                  // Field this$0:LTest;
         5: aload_0
         6: invokespecial #2                  // Method Merchant."<init>":()V
         9: return
      LineNumberTable:
        line 36: 0
      LocalVariableTable:
        Start  Length  Slot  Name   Signature
            0      10     0  this   LTest$VIPOnlyMerchant;
            0      10     1 this$0   LTest;

  public double actionPrice(double, VIP);
    descriptor: (DLVIP;)D
    flags: (0x0001) ACC_PUBLIC
    Code:
      stack=2, locals=4, args_size=3
         0: ldc2_w        #3                  // double 0.1d
         3: dreturn
      LineNumberTable:
        line 39: 0
      LocalVariableTable:
        Start  Length  Slot  Name   Signature
            0       4     0  this   LTest$VIPOnlyMerchant;
            0       4     1 price   D
            0       4     3 customer   LVIP;

  public double actionPrice(double, Customer);
    descriptor: (DLCustomer;)D
    flags: (0x1041) ACC_PUBLIC, ACC_BRIDGE, ACC_SYNTHETIC
    Code:
      stack=4, locals=4, args_size=3
         0: aload_0
         1: dload_1
         2: aload_3
         3: checkcast     #5                  // class VIP
         6: invokevirtual #6                  // Method actionPrice:(DLVIP;)D
         9: dreturn
      LineNumberTable:
        line 36: 0
      LocalVariableTable:
        Start  Length  Slot  Name   Signature
            0      10     0  this   LTest$VIPOnlyMerchant;
}
Signature: #28                          // LMerchant<LVIP;>;
SourceFile: "Test.java"
InnerClasses:
  #17= #7 of #35;                         // VIPOnlyMerchant=class Test$VIPOnlyMerchant of class Test
```


将内部类变为static后再次查看，已经不再持有外部类的引用了 
```
Classfile /home/song/WorkSpace/IdeaWorkSpace/DataStruct/out/production/DataStruct/Test$VIPOnlyMerchant.class
  Last modified 2022年3月30日; size 714 bytes
  MD5 checksum f2b3dfed8341f873bbb1fab43addab01
  Compiled from "Test.java"
class Test$VIPOnlyMerchant extends Test$Merchant<Test$VIP>
  minor version: 0
  major version: 52
  flags: (0x0020) ACC_SUPER
  this_class: #6                          // Test$VIPOnlyMerchant
  super_class: #7                         // Test$Merchant
  interfaces: 0, fields: 0, methods: 3, attributes: 3
Constant pool:
   ...///省略常量池
{
  Test$VIPOnlyMerchant();
    descriptor: ()V
    flags: (0x0000)
    Code:
      stack=1, locals=1, args_size=1
         0: aload_0
         1: invokespecial #1                  // Method Test$Merchant."<init>":()V
         4: return
      LineNumberTable:
        line 49: 0
      LocalVariableTable:
        Start  Length  Slot  Name   Signature
            0       5     0  this   LTest$VIPOnlyMerchant;

  public double actionPrice(double, Test$VIP);
    descriptor: (DLTest$VIP;)D
    flags: (0x0001) ACC_PUBLIC
    Code:
      stack=2, locals=4, args_size=3
         0: ldc2_w        #2                  // double 0.1d
         3: dreturn
      LineNumberTable:
        line 52: 0
      LocalVariableTable:
        Start  Length  Slot  Name   Signature
            0       4     0  this   LTest$VIPOnlyMerchant;
            0       4     1 price   D
            0       4     3 customer   LTest$VIP;

  public double actionPrice(double, Test$Customer);
    descriptor: (DLTest$Customer;)D
    flags: (0x1041) ACC_PUBLIC, ACC_BRIDGE, ACC_SYNTHETIC
    Code:
      stack=4, locals=4, args_size=3
         0: aload_0
         1: dload_1
         2: aload_3
         3: checkcast     #4                  // class Test$VIP
         6: invokevirtual #5                  // Method actionPrice:(DLTest$VIP;)D
         9: dreturn
      LineNumberTable:
        line 49: 0
      LocalVariableTable:
        Start  Length  Slot  Name   Signature
            0      10     0  this   LTest$VIPOnlyMerchant;
}
Signature: #29                          // LTest$Merchant<LTest$VIP;>;
SourceFile: "Test.java"
InnerClasses:
  static #14= #6 of #33;                  // VIPOnlyMerchant=class Test$VIPOnlyMerchant of class Test
  static #18= #4 of #33;                  // VIP=class Test$VIP of class Test
  static #25= #24 of #33;                 // Customer=class Test$Customer of class Test
  static #28= #7 of #33;                  // Merchant=class Test$Merchant of class Test
```


匿名内部类
增加一个文件 外部类$1.class
每有一个内部类，数字增加1，外部的局部变量声明为final，在构造器时进行赋值，与外部引用相似
```
public class Test {
    public static void main(String[] args)  {
       Test test=new Test();
       test.show();
    }
    private void show() {
        int a = 11;
        ParentGeneric<String> p = new ParentGeneric<String>(){
            @Override
            void name() {
                super.name();
                System.out.println(a);
            }
        };
        p.name();
    }
   public class ParentGeneric<T> {
        void name(){}
    }
}
```
字节码
```
Classfile /home/song/WorkSpace/IdeaWorkSpace/DataStruct/out/production/DataStruct/Test$1.class
  Last modified 2022年3月30日; size 733 bytes
  MD5 checksum bcfadb51fb51b64c02fe26a3a4accb60
  Compiled from "Test.java"
class Test$1 extends Test$ParentGeneric<java.lang.String>
  minor version: 0
  major version: 52
  flags: (0x0020) ACC_SUPER
  this_class: #7                          // Test$1
  super_class: #8                         // Test$ParentGeneric
  interfaces: 0, fields: 2, methods: 2, attributes: 4
Constant pool:
 ...//省略常量池
{
  final int val$a;
    descriptor: I
    flags: (0x1010) ACC_FINAL, ACC_SYNTHETIC

  final Test this$0;
    descriptor: LTest;
    flags: (0x1010) ACC_FINAL, ACC_SYNTHETIC

  Test$1(Test, int);
    descriptor: (LTest;I)V
    flags: (0x0000)
    Code:
      stack=2, locals=3, args_size=3
         0: aload_0
         1: aload_1
         2: putfield      #1                  // Field this$0:LTest;
         5: aload_0
         6: iload_2
         7: putfield      #2                  // Field val$a:I
        10: aload_0
        11: aload_1
        12: invokespecial #3                  // Method Test$ParentGeneric."<init>":(LTest;)V
        15: return
      LineNumberTable:
        line 22: 0
      LocalVariableTable:
        Start  Length  Slot  Name   Signature
            0      16     0  this   LTest$1;
            0      16     1 this$0   LTest;

  void name();
    descriptor: ()V
    flags: (0x0000)
    Code:
      stack=2, locals=1, args_size=1
         0: aload_0
         1: invokespecial #4                  // Method Test$ParentGeneric.name:()V
         4: getstatic     #5                  // Field java/lang/System.out:Ljava/io/PrintStream;
         7: aload_0
         8: getfield      #2                  // Field val$a:I
        11: invokevirtual #6                  // Method java/io/PrintStream.println:(I)V
        14: return
      LineNumberTable:
        line 25: 0
        line 26: 4
        line 27: 14
      LocalVariableTable:
        Start  Length  Slot  Name   Signature
            0      15     0  this   LTest$1;
}
Signature: #25                          // LTest$ParentGeneric<Ljava/lang/String;>;
SourceFile: "Test.java"
EnclosingMethod: #29.#30                // Test.show
InnerClasses:
  #7;                                     // class Test$1
  public #24= #8 of #29;                  // ParentGeneric=class Test$ParentGeneric of class Test

```